Metadata-Version: 1.1
Name: benbaptist-elevenlabs
Version: 0.1.1
Summary: An unofficial Python library for integrating with ElevenLabs.io's API
Home-page: https://github.com/benbaptist/elevenlabs
Author: Ben Baptist
Author-email: me@benbaptist.com
License: UNKNOWN
Platform: UNKNOWN
Classifier: Development Status :: 2 - Pre-Alpha
Classifier: Intended Audience :: Developers
Classifier: License :: OSI Approved :: MIT License
Classifier: Programming Language :: Python :: 3
Classifier: Programming Language :: Python :: 3.7
Classifier: Programming Language :: Python :: 3.8
